toolbox/__init__.py
toolbox/argparse_mod.py
toolbox/click_complete.py
toolbox/curl.py
toolbox/curl2.py
toolbox/emoji.lst
toolbox/fernet.py
toolbox/getpass.py
toolbox/jsontools.py
toolbox/logger.py
toolbox/menuboard.py
toolbox/menumaker.py
toolbox/misc.py
toolbox/results.py
toolbox/stage_accounts.lst
toolbox/utils.py
goattoolbox-2024.7.16.1623.dist-info/METADATA
goattoolbox-2024.7.16.1623.dist-info/WHEEL
goattoolbox-2024.7.16.1623.dist-info/top_level.txt
goattoolbox-2024.7.16.1623.dist-info/RECORD
