Metadata-Version: 2.1
Name: goattoolbox
Version: 2024.7.16.1623
Summary: toolbox - a library of standalone python modules ready for use
Author-email: Chris Stacks <centerupt@gmail.com>
Classifier: Programming Language :: Python :: 3
Classifier: Operating System :: OS Independent
Requires-Python: >=3.7
Requires-Dist: argparse
Requires-Dist: pync
Requires-Dist: gnupg
Requires-Dist: cryptography
Requires-Dist: rich
